{"_type":"export","__export_format":4,"__export_date":"2019-12-04T18:50:57.227Z","__export_source":"insomnia.desktop.app:v7.0.5","resources":[{"_id":"req_9cbbddc238d14e7f807599d35e4663ac","authentication":{},"body":{},"created":1575480250748,"description":"","headers":[],"isPrivate":false,"metaSortKey":-1575480250748,"method":"GET","modified":1575480256624,"name":"/","parameters":[],"parentId":"wrk_9219c3138a49495abfd3a44c9551e74d","settingDisableRenderRequestBody":false,"settingEncodeUrl":true,"settingFollowRedirects":"global","settingRebuildPath":true,"settingSendCookies":true,"settingStoreCookies":true,"url":"localhost:4000","_type":"request"},{"_id":"wrk_9219c3138a49495abfd3a44c9551e74d","created":1575305243968,"description":"","modified":1575305243968,"name":"Insomnia","parentId":null,"_type":"workspace"},{"_id":"req_0fafa1301ac448228b4381a103e485f5","authentication":{},"body":{},"created":1575485195501,"description":"","headers":[{"description":"","id":"pair_34d2dee8ea4a48daa63cf13a21ff68c5","name":"role","value":"admin"}],"isPrivate":false,"metaSortKey":-1575480250723,"method":"GET","modified":1575485211071,"name":"/api/hubs","parameters":[],"parentId":"wrk_9219c3138a49495abfd3a44c9551e74d","settingDisableRenderRequestBody":false,"settingEncodeUrl":true,"settingFollowRedirects":"global","settingRebuildPath":true,"settingSendCookies":true,"settingStoreCookies":true,"url":"localhost:4000","_type":"request"},{"_id":"req_d95eaed34f44453292d1bb33a5d044b9","authentication":{},"body":{},"created":1575480609654,"description":"","headers":[],"isPrivate":false,"metaSortKey":-1575480250698,"method":"GET","modified":1575480616051,"name":"/echo","parameters":[],"parentId":"wrk_9219c3138a49495abfd3a44c9551e74d","settingDisableRenderRequestBody":false,"settingEncodeUrl":true,"settingFollowRedirects":"global","settingRebuildPath":true,"settingSendCookies":true,"settingStoreCookies":true,"url":"localhost:4000/echo","_type":"request"},{"_id":"req_422ac4b0b75042e98292ddb67d71f6c8","authentication":{},"body":{},"created":1575480627269,"description":"","headers":[{"description":"","id":"pair_2c20aa48cf314ed3aec83e11945f67f0","name":"password","value":"mellon"},{"description":"","id":"pair_4843cdf6f7414e60a0a7ff67b35cf206","name":"role","value":"agent"}],"isPrivate":false,"metaSortKey":-1575480250648,"method":"GET","modified":1575485180831,"name":"/area51","parameters":[],"parentId":"wrk_9219c3138a49495abfd3a44c9551e74d","settingDisableRenderRequestBody":false,"settingEncodeUrl":true,"settingFollowRedirects":"global","settingRebuildPath":true,"settingSendCookies":true,"settingStoreCookies":true,"url":"localhost:4000/area51","_type":"request"},{"_id":"env_bea0d82cc658dbed88bcdd6750f0aac22c035e43","color":null,"created":1575305244035,"data":{},"dataPropertyOrder":null,"isPrivate":false,"metaSortKey":1575305244035,"modified":1575305244035,"name":"Base Environment","parentId":"wrk_9219c3138a49495abfd3a44c9551e74d","_type":"environment"},{"_id":"jar_bea0d82cc658dbed88bcdd6750f0aac22c035e43","cookies":[],"created":1575305244045,"modified":1575305244045,"name":"Default Jar","parentId":"wrk_9219c3138a49495abfd3a44c9551e74d","_type":"cookie_jar"}]}